hpsklearn/__init__.py
hpsklearn/components/__init__.py
hpsklearn/components/_base.py
hpsklearn/components/discriminant_analysis.py
hpsklearn/components/dummy.py
hpsklearn/components/kernel_ridge.py
hpsklearn/components/lagselectors.py
hpsklearn/components/lightgbm.py
hpsklearn/components/multiclass.py
hpsklearn/components/naive_bayes.py
hpsklearn/components/vkmeans.py
hpsklearn/components/xgboost.py
hpsklearn/components/cluster/__init__.py
hpsklearn/components/cluster/_kmeans.py
hpsklearn/components/compose/__init__.py
hpsklearn/components/compose/_target.py
hpsklearn/components/covariance/__init__.py
hpsklearn/components/covariance/_elliptic_envelope.py
hpsklearn/components/cross_decomposition/__init__.py
hpsklearn/components/cross_decomposition/_pls.py
hpsklearn/components/decomposition/__init__.py
hpsklearn/components/decomposition/_pca.py
hpsklearn/components/ensemble/__init__.py
hpsklearn/components/ensemble/_bagging.py
hpsklearn/components/ensemble/_forest.py
hpsklearn/components/ensemble/_gb.py
hpsklearn/components/ensemble/_hist_gradient_boosting.py
hpsklearn/components/ensemble/_iforest.py
hpsklearn/components/ensemble/_weight_boosting.py
hpsklearn/components/feature_extraction/__init__.py
hpsklearn/components/feature_extraction/text.py
hpsklearn/components/gaussian_process/__init__.py
hpsklearn/components/gaussian_process/_gpc.py
hpsklearn/components/gaussian_process/_gpr.py
hpsklearn/components/linear_model/__init__.py
hpsklearn/components/linear_model/_base.py
hpsklearn/components/linear_model/_bayes.py
hpsklearn/components/linear_model/_coordinate_descent.py
hpsklearn/components/linear_model/_glm.py
hpsklearn/components/linear_model/_huber.py
hpsklearn/components/linear_model/_least_angle.py
hpsklearn/components/linear_model/_logistic.py
hpsklearn/components/linear_model/_omp.py
hpsklearn/components/linear_model/_passive_aggressive.py
hpsklearn/components/linear_model/_perceptron.py
hpsklearn/components/linear_model/_quantile.py
hyperopt_sklearn-1.1.1.dist-info/licenses/LICENSE.txt
hyperopt_sklearn-1.1.1.dist-info/METADATA
hyperopt_sklearn-1.1.1.dist-info/WHEEL
hyperopt_sklearn-1.1.1.dist-info/top_level.txt
hyperopt_sklearn-1.1.1.dist-info/RECORD
