Metadata-Version: 2.4
Name: hyperopt-sklearn
Version: 1.1.1
Summary: Hyperparameter Optimization for sklearn
Home-page: https://github.com/hyperopt/hyperopt-sklearn/
Author: James Bergstra
Author-email: anon@anon.com
Maintainer: Pim Tholhuijsen
Maintainer-email: anon@anon.com
License: BSD
Keywords: hyperopt,hyperparameter,sklearn
Platform: Linux
Platform: OS-X
Platform: Windows
Classifier: Development Status :: 3 - Alpha
Classifier: Intended Audience :: Education
Classifier: Intended Audience :: Science/Research
Classifier: Intended Audience :: Developers
Classifier: Environment :: Console
Classifier: License :: OSI Approved :: BSD License
Classifier: Operating System :: MacOS :: MacOS X
Classifier: Operating System :: Microsoft :: Windows
Classifier: Operating System :: POSIX
Classifier: Operating System :: Unix
Classifier: Programming Language :: Python :: 3
Classifier: Programming Language :: Python :: 3 :: Only
Classifier: Programming Language :: Python :: 3.11
Classifier: Programming Language :: Python :: 3.12
Classifier: Programming Language :: Python :: 3.13
Classifier: Topic :: Scientific/Engineering
Classifier: Topic :: Software Development
Requires-Python: >=3.11
License-File: LICENSE.txt
Requires-Dist: hyperopt==0.2.7
Requires-Dist: numpy<=2.3.0,>=2.0.0
Requires-Dist: scikit-learn<=1.7,>=1.5
Requires-Dist: scipy<=1.15.3,>=1.15.0
Requires-Dist: pandas<=2.3.0,>=2.1.0
Requires-Dist: setuptools>=71.0.0
Provides-Extra: xgboost
Requires-Dist: xgboost<=2.2.0,>=2.0.0; extra == "xgboost"
Provides-Extra: lightgbm
Requires-Dist: lightgbm==4.6.0; extra == "lightgbm"
Provides-Extra: testing
Requires-Dist: tox>=4.20.0; extra == "testing"
Requires-Dist: coverage==7.6.12; extra == "testing"
Dynamic: license-file
